{"operationId":"RestV10PotentialChangeOrdersPotentialChangeOrderIdLineItemsSyncPatch","method":"PATCH","path":"/rest/v1.0/potential_change_orders/{potential_change_order_id}/line_items/sync","summary":"Sync Potential Change Order Line Items","description":"This endpoint creates or updates a batch of Potential Change Order Line Items.\nSee [Using Sync Actions](/documentation/using-sync-actions) for additional information.","tag":"Construction Financials/Change Orders/potential-change-orders","parameters":[{"name":"project_id","in":"query","required":true,"description":"Unique identifier for the project.","schema":{"type":"integer"}},{"name":"potential_change_order_id","in":"path","required":true,"description":"Potential Change Order ID","schema":{"type":"integer"}}],"responses":{"200":{"description":"Array of Potential Change Order Line Items","schema":{"type":"object","properties":{"entities":{"type":"array","items":{"type":"object","description":"Line Item (when the 'default' view is requested)","properties":{"id":{"type":"integer","description":"Line Item id"},"amount":{"type":"string","description":"Line Item amount"},"company":{"type":"object","description":"Company","properties":{"id":{"type":"object","description":"(nested object)"},"name":{"type":"object","description":"(nested object)"}}},"cost_code":{"type":"object","properties":{"id":{"type":"object","description":"(nested object)"},"biller":{"type":"object","description":"(nested object)"},"biller_id":{"type":"object","description":"(nested object)"},"biller_type":{"type":"object","description":"(nested object)"},"budgeted":{"type":"object","description":"(nested object)"},"code":{"type":"object","description":"(nested object)"},"created_at":{"type":"object","description":"(nested object)"},"deleted_at":{"type":"object","description":"(nested object)"},"full_code":{"type":"object","description":"(nested object)"},"name":{"type":"object","description":"(nested object)"},"origin_data":{"type":"object","description":"(nested object)"},"origin_id":{"type":"object","description":"(nested object)"},"parent":{"type":"object","description":"(nested object)"},"position":{"type":"object","description":"(nested object)"},"sortable_code":{"type":"object","description":"(nested object)"},"standard_cost_code_id":{"type":"object","description":"(nested object)"},"standard_cost_code_list_id":{"type":"object","description":"(nested object)"},"updated_at":{"type":"object","description":"(nested object)"},"line_item_types":{"type":"object","description":"(nested object)"}}},"created_at":{"type":"string","description":"Created at date and time","format":"date-time"},"description":{"type":"string","description":"Line Item description"},"extended_type":{"type":"string","description":"Line Item extended type","enum":["manual","calculated"]},"holder":{"type":"object","description":"Holder","properties":{"id":{"type":"object","description":"(nested object)"},"holder_type":{"type":"object","description":"(nested object)"}}},"line_item_type":{"type":"object","description":"Line Item Type","properties":{"id":{"type":"object","description":"(nested object)"},"name":{"type":"object","description":"(nested object)"},"code":{"type":"object","description":"(nested object)"},"base_type":{"type":"object","description":"(nested object)"},"origin_data":{"type":"object","description":"(nested object)"},"origin_id":{"type":"object","description":"(nested object)"}}},"origin_data":{"type":"string","description":"Line Item third party data"},"origin_id":{"type":"string","description":"Line Item third party id"},"position":{"type":"integer","description":"Line Item position"},"project":{"type":"object","description":"Project","properties":{"id":{"type":"object","description":"(nested object)"},"name":{"type":"object","description":"(nested object)"}}},"quantity":{"type":"string","description":"Line Item quantity","format":"float"},"tax_code_id":{"type":"integer","description":"Tax Code ID"},"total_amount":{"type":"string","description":"Line Item total amount","format":"float"},"extended_amount":{"type":"string","description":"Line Item extended amount","format":"float"},"unit_cost":{"type":"string","description":"Line Item unit cost","format":"float"},"uom":{"type":"string","description":"Line Item units of measure"},"wbs_code":{"type":"object","properties":{"id":{"type":"object","description":"(nested object)"},"flat_code":{"type":"object","description":"(nested object)"},"description":{"type":"object","description":"(nested object)"}}},"updated_at":{"type":"string","description":"Updated at date and time","format":"date-time"},"change_event_line_item":{"type":"object","description":"Change Event Line Item","properties":{"id":{"type":"object","description":"(nested object)"},"cost_rom":{"type":"object","description":"(nested object)"},"revenue_rom":{"type":"object","description":"(nested object)"},"event_id":{"type":"object","description":"(nested object)"},"cost_code":{"type":"object","description":"(nested object)"},"line_item_type":{"type":"object","description":"(nested object)"},"currency_configuration":{"type":"object","description":"(nested object)"}}},"currency_configuration":{"type":"object","properties":{"currency_iso_code":{"type":"object","description":"(nested object)"}}}}}},"errors":{"type":"array","items":{"type":"object"}}}}},"400":{"description":"Bad Request"},"401":{"description":"Unauthorized"},"403":{"description":"Forbidden"},"default":{"description":"Unexpected error"}},"requestBody":{"contentType":"application/json","required":true,"schema":{"type":"object","required":["updates"],"properties":{"updates":{"type":"array","items":{"type":"object","description":"The Line Item object","properties":{"amount":{"type":"string","description":"Amount"},"cost_code_id":{"type":"integer","description":"Cost Code ID"},"description":{"type":"string","description":"Description"},"extended_type":{"type":"string","description":"Extended type","enum":["manual","calculated"]},"quantity":{"type":"string","description":"Quantity"},"line_item_type_id":{"type":"integer","description":"Line Item Type ID"},"origin_data":{"type":"string","description":"Origin Data"},"origin_id":{"type":"string","description":"Origin ID"},"tax_code_id":{"type":"integer","description":"Tax Code ID"},"unit_cost":{"type":"string","description":"Unit cost"},"uom":{"type":"string","description":"Unit of measure","enum":["Any value present in the Company list of Units of Measure"]},"wbs_code_id":{"type":"integer","description":"WBS code ID"}}}}}}}}