{"operationId":"RestV10CompaniesCompanyIdProjectsProjectIdContextsContextIdLayersGet","method":"GET","path":"/rest/v1.0/companies/{company_id}/projects/{project_id}/contexts/{context_id}/layers","summary":"Get layers for context","description":"Retrieve all layers within a specific context","tag":"Project Management/Document Markup/layer","parameters":[{"name":"company_id","in":"path","required":true,"description":"","schema":{"type":"string"}},{"name":"project_id","in":"path","required":true,"description":"","schema":{"type":"string"}},{"name":"context_id","in":"path","required":true,"description":"","schema":{"type":"string"}},{"name":"page","in":"query","required":false,"description":"","schema":{"type":"integer","format":"int32","default":1}},{"name":"per_page","in":"query","required":false,"description":"","schema":{"type":"integer","format":"int32","default":20}}],"responses":{"200":{"description":"OK"}}}