{"operationId":"RestV10ProjectsProjectIdActionPlansPlanTemplateReferencesIdDelete","method":"DELETE","path":"/rest/v1.0/projects/{project_id}/action_plans/plan_template_references/{id}","summary":"Delete Project Action Plan Template Reference","description":"Deletes a Project Action Plan Template Reference","tag":"Project Management/Action Plans/project-action-plan-template-references","parameters":[{"name":"project_id","in":"path","required":true,"description":"Unique identifier for the project.","schema":{"type":"integer"}},{"name":"id","in":"path","required":true,"description":"Project Action Plan Template Reference ID","schema":{"type":"integer"}}],"responses":{"204":{"description":"No Content"},"401":{"description":"Unauthorized"},"403":{"description":"Forbidden"},"404":{"description":"Not Found"},"409":{"description":"Conflict"},"422":{"description":"Unprocessable Entity"}}}