{"operationId":"RestV10ProjectsProjectIdTimeAndMaterialEntryAttachmentsIdDelete","method":"DELETE","path":"/rest/v1.0/projects/{project_id}/time_and_material_entry_attachments/{id}","summary":"Delete a Time and Material Attachment","description":"Deleting a Time and Material Attachment from a specified Project","tag":"Project Management/Field Productivity/time-and-material-attachment","parameters":[{"name":"project_id","in":"path","required":true,"description":"Unique identifier for the project.","schema":{"type":"integer"}},{"name":"id","in":"path","required":true,"description":"ID of the time and material attachment","schema":{"type":"integer"}}],"responses":{"200":{"description":"OK","schema":{"type":"object","description":"Time and Material Entry Attachment","properties":{"id":{"type":"integer","description":"ID"},"attachment_id":{"type":"integer","description":"ID of the associated prostore file"},"content_type":{"type":"string","description":"Content type"},"presentation_url":{"type":"string","description":"URL"},"url":{"type":"string","description":"URL"},"thumbnail_url":{"type":"string","description":"URL"},"filename":{"type":"string","description":"Filename of Time and Material Entry Attachment"}}}},"403":{"description":"Forbidden"},"404":{"description":"Not found"}}}