{"operationId":"RestV10WorkflowInstancesIdGet","method":"GET","path":"/rest/v1.0/workflow_instances/{id}","summary":"Show Workflow Instance","description":"Get information about a Workflow Instance","tag":"Core/Workflows/legacy---workflow-instances","parameters":[{"name":"company_id","in":"query","required":true,"description":"Unique identifier for the company.","schema":{"type":"integer"}},{"name":"id","in":"path","required":true,"description":"ID","schema":{"type":"integer"}}],"responses":{"200":{"description":"OK","schema":{"type":"object","description":"Workflow Instance","properties":{"id":{"type":"integer","description":"ID"},"becomes_overdue_at":{"type":"string","description":"Workflowed Object is considered overdue after","format":"date-time"},"current_state_set_at":{"type":"string","description":"Workflow entered the current state at","format":"date-time"},"workflowed_object_id":{"type":"integer","description":"Workflowed Object ID"},"workflowed_object_type":{"type":"string","description":"The Type of the Workflowed Object"},"project":{"type":"object","properties":{"name":{"type":"string","description":"Name of the associated project"},"id":{"type":"integer","description":"Unique identifier for the project."}}},"current_workflow_activities":{"type":"array","items":{"type":"object","description":"Workflow Activity","properties":{"id":{"type":"integer","description":"ID"},"name":{"type":"string","description":"Name"},"workflow_user_role":{"type":"object","description":"Workflow User Role","properties":{"id":{"type":"object","description":"(nested object)"},"name":{"type":"object","description":"(nested object)"},"assignee":{"type":"object","description":"(nested object)"}}},"perform_activity":{"type":"object","description":"Endpoint to perform Workflow Activities","properties":{"url":{"type":"object","description":"(nested object)"},"method":{"type":"object","description":"(nested object)"},"data":{"type":"object","description":"(nested object)"}}}}}},"current_workflow_state":{"type":"object","description":"Workflow State","properties":{"id":{"type":"integer","description":"ID"},"name":{"type":"string","description":"Name"},"status":{"type":"string","description":"Status"}}},"workflow":{"type":"object","description":"Workflow","properties":{"id":{"type":"integer","description":"ID"},"name":{"type":"string","description":"Name"},"description":{"type":"string","description":"Description"},"class_name":{"type":"string","description":"Class Name"},"created_at":{"type":"string","description":"Created at","format":"date-time"},"updated_at":{"type":"string","description":"Created at","format":"date-time"},"domain":{"type":"string","description":"Domain name"}}}}}},"400":{"description":"Bad Request"}}}