{"operationId":"RestV11ProjectsProjectIdMeetingsEcrionPdfGenerationDataGet","method":"GET","path":"/rest/v1.1/projects/{project_id}/meetings/ecrion_pdf_generation_data","summary":"List Ecrion Xml and Template for Meetings","description":"Returns Ecrion Xml and Template for all Meetings on the Project.","tag":"Project Management/Meetings/meetings","parameters":[{"name":"project_id","in":"path","required":true,"description":"Unique identifier for the project.","schema":{"type":"integer"}},{"name":"page","in":"query","required":false,"description":"Page","schema":{"type":"integer"}},{"name":"per_page","in":"query","required":false,"description":"Elements per page","schema":{"type":"integer"}},{"name":"filters[assignee_id]","in":"query","required":false,"description":"Returns meeting(s) with the specified assignee","schema":{"type":"array","description":"Array of assignee IDs","items":{"type":"integer"}}},{"name":"filters[id]","in":"query","required":false,"description":"Returns meeting(s) with the specified ID(s)","schema":{"type":"array","description":"Array of meeting IDs","items":{"type":"integer"}}},{"name":"filters[public]","in":"query","required":false,"description":"Returns public meeting(s).","schema":{"type":"string"}},{"name":"filters[draft]","in":"query","required":false,"description":"Returns draft meeting(s).","schema":{"type":"string"}},{"name":"filters[mode]","in":"query","required":false,"description":"Returns meeting(s) in certain mode.","schema":{"type":"string","enum":["agenda","meetings"]}},{"name":"filters[root_id]","in":"query","required":false,"description":"Returns child meeting(s) whose root_id matches the specified root_id. Parent is returned as well","schema":{"type":"string"}},{"name":"filters[roots]","in":"query","required":false,"description":"Returns Only parent/root meetings","schema":{"type":"string"}},{"name":"filters[template_id]","in":"query","required":false,"description":"Returns child meeting(s) whose meeting_template_id matches the specified template_id.","schema":{"type":"string"}},{"name":"show_attachments","in":"query","required":false,"description":"determine the AttachmentVisible tag value","schema":{"type":"boolean"}}],"responses":{"200":{"description":"Ecrion Template and Xml returned successfully","schema":{"type":"object","properties":{"pdf_template":{"type":"object","properties":{"uuid":{"type":"string","description":"uuid of the PdfTemplate"},"pdf_filename":{"type":"string","description":"Filename of the PdfTemplate"},"name":{"type":"string","description":"Name of the PdfTemplate"},"url":{"type":"string","description":"url of the PdfTemplate"},"storage_type":{"type":"string","description":"The storage type for the pdf to be passed to ecrion. Should be govcloud or default."}}},"meetings":{"type":"array","items":{"type":"object","properties":{"id":{"type":"integer"},"name":{"type":"string","description":"The name for the ecrion pdf."},"xml":{"type":"string","description":"The Ecrion xml for the Meeting."}}}}}}},"401":{"description":"Unauthorized"},"403":{"description":"Forbidden"}}}