{"operationId":"RestV10ProjectsProjectIdDrawingSetsGet","method":"GET","path":"/rest/v1.0/projects/{project_id}/drawing_sets","summary":"List drawing sets","description":"Lists the Drawing Sets in the specified Project.","tag":"Project Management/Drawings/drawings","parameters":[{"name":"project_id","in":"path","required":true,"description":"Unique identifier for the project.","schema":{"type":"integer"}},{"name":"page","in":"query","required":false,"description":"Page","schema":{"type":"integer"}},{"name":"per_page","in":"query","required":false,"description":"Elements per page","schema":{"type":"integer"}},{"name":"filters[exclude_empty_sets]","in":"query","required":false,"description":"If true, returns drawing sets that contain at least one drawing.","schema":{"type":"boolean"}},{"name":"filters[only_attachable_sets]","in":"query","required":false,"description":"If true, returns drawing sets that contain at least one published drawing.","schema":{"type":"boolean"}},{"name":"filters[with_sketches]","in":"query","required":false,"description":"If true, returns only drawing sets that contain at least one drawing sketch.","schema":{"type":"boolean"}},{"name":"filters[with_measurements]","in":"query","required":false,"description":"If true, returns only drawing sets that contain at least one measurement.","schema":{"type":"boolean"}},{"name":"drawing_area_id","in":"query","required":false,"description":"Filters to only drawing sets with a least one revision in that drawing area.","schema":{"type":"integer"}}],"responses":{"200":{"description":"OK","schema":{"type":"array","description":"Array of drawing sets","items":{"type":"object","description":"Drawing Set","properties":{"id":{"type":"integer","description":"Drawing Set ID"},"project_id":{"type":"integer","description":"Drawing Set project ID"},"company_id":{"type":"integer","description":"Drawing Set company ID"},"name":{"type":"string","description":"Drawing Set name"},"created_at":{"type":"string","description":"Drawing Set created at","format":"date-time"},"updated_at":{"type":"string","description":"Drawing Set updated at","format":"date-time"},"date":{"type":"string","description":"Drawing Set date","format":"date"},"position":{"type":"integer","description":"Drawing Set position"},"connected":{"type":"boolean","description":"Drawing Set is connected"},"deletable":{"type":"boolean","description":"This field is deprecated and will always return false. It does not indicate whether the drawing set can be deleted or not."},"published_drawings_count":{"type":"integer","description":"Number of published Drawing Revisions in the Drawing Set. Requires a drawing_area_id param."},"unpublished_drawings_count":{"type":"integer","description":"Number of unpublished Drawing Revisions in the Drawing Set. Requires a drawing_area_id param."}}}}},"401":{"description":"Unauthorized"},"403":{"description":"Forbidden"},"default":{"description":"Unexpected error"}}}