{"operationId":"RestV10ProjectsProjectIdDailyLogHeadersGet","method":"GET","path":"/rest/v1.0/projects/{project_id}/daily_log_headers","summary":"Get the Daily Log Header via date or id","description":"Returns the Daily Log Header for a given date or id","tag":"Project Management/Daily Log/daily-log-headers","parameters":[{"name":"project_id","in":"path","required":true,"description":"Unique identifier for the project.","schema":{"type":"integer"}},{"name":"id","in":"query","required":false,"description":"The id of the requested Daily Log Header","schema":{"type":"integer"}},{"name":"log_date","in":"query","required":false,"description":"The log date for the requested Daily Log Header","schema":{"type":"string","format":"date"}}],"responses":{"200":{"description":"OK","schema":{"type":"object","description":"A daily log header","properties":{"id":{"type":"integer","description":"The id of the daily log header"},"log_date":{"type":"string","description":"Date that this daily log header represents Format: YYYY-MM-DD Example: 2016-05-19","format":"date"},"log_datetime":{"type":"string","description":"Estimated UTC datetime that this daily log header represents","format":"date-time"},"completed":{"type":"boolean","description":"Is this log date marked as complete?"},"completed_by":{"type":"object","properties":{"id":{"type":"integer","description":"ID"},"login":{"type":"string","description":"Email"},"name":{"type":"string","description":"Name"}}},"completed_at":{"type":"string","description":"Daily log header marked complete at","format":"date-time"},"completable":{"type":"boolean","description":"Is this log date able to be completed?"},"distributed":{"type":"boolean","description":"Is this log date marked as distributed?"},"distributed_by":{"type":"object","properties":{"id":{"type":"integer","description":"ID"},"login":{"type":"string","description":"Email"},"name":{"type":"string","description":"Name"}}},"distributed_at":{"type":"string","description":"Daily log header marked distributed at","format":"date-time"},"distributable":{"type":"boolean","description":"Is this log date able to be distributed?"}}}},"403":{"description":"User does not have permissions to view the requested Daily Log Header"}}}