{"operationId":"RestV10ObservationsItemsSendUnsentPost","method":"POST","path":"/rest/v1.0/observations/items/send_unsent","summary":"Send unsent Observation Items","description":"Sends email notifications for unsent Observation Items.","tag":"Project Management/Observations/observations","parameters":[],"responses":{"200":{"description":"OK","schema":{"type":"array","items":{"type":"object","properties":{"id":{"type":"integer","description":"Observation Item ID"},"created_at":{"type":"string","description":"Created at","format":"date-time"},"closed_at":{"type":"string","description":"Closed at","format":"date-time"},"deleted_at":{"type":"string","description":"Deleted at","format":"date-time"},"updated_at":{"type":"string","description":"Updated at","format":"date-time"},"number":{"type":"string","description":"Observation Item number"},"name":{"type":"string","description":"Observation Item name"},"description":{"type":"string","description":"Observation Item description"},"description_rich_text":{"type":"string","description":"Observation Item description"},"status":{"type":"string","description":"Observation Item status","enum":["initiated","ready_for_review","not_accepted","closed"]},"priority":{"type":"string","description":"Observation Item priority","enum":["Low","Medium","High","Urgent"]},"date_notified":{"type":"string","description":"Date that the Observation Item Assignee was notified","format":"date"},"due_date":{"type":"string","description":"Date that the Observation Item is due by","format":"date"},"personal":{"type":"boolean","description":"Observation Item privacy status"},"origin":{"type":"object","description":"Origin Item that the Observation was created from","properties":{"type":{"type":"string","description":"Origin Type","enum":["incident","bim_model","inspection","coordination_issue"]},"payload":{"type":"object","description":"Payload Keys change depending on origin.","properties":{"checklist_item_id":{"type":"object","description":"(nested object)"},"checklist_list_id":{"type":"object","description":"(nested object)"},"coordination_issue_id":{"type":"object","description":"(nested object)"},"coordination_issue_number":{"type":"object","description":"(nested object)"},"incident_action_id":{"type":"object","description":"(nested object)"},"incident_id":{"type":"object","description":"(nested object)"},"bim_model_id":{"type":"object","description":"(nested object)"},"bim_model_name":{"type":"object","description":"(nested object)"}}}}},"assignee":{"type":"object","properties":{"id":{"type":"integer","description":"User ID"},"name":{"type":"string","description":"User's name"},"vendor":{"type":"object","description":"Company of User assigned to the Observation Item","properties":{"id":{"type":"object","description":"(nested object)"},"name":{"type":"object","description":"(nested object)"}}}}},"created_by":{"type":"object","properties":{"id":{"type":"integer","description":"ID"},"login":{"type":"string","description":"Email"},"name":{"type":"string","description":"Name"}}},"location":{"type":"object","properties":{"id":{"type":"integer","description":"Location ID"},"name":{"type":"string","description":"Location name"},"node_name":{"type":"string","description":"Location node name"},"parent_id":{"type":"integer","description":"Location parent id"},"created_at":{"type":"string","description":"Timestamp of Location creation","format":"date-time"},"updated_at":{"type":"string","description":"Timestamp of last update to Location","format":"date-time"}}},"specification_section":{"type":"object","description":"Specification Section","properties":{"id":{"type":"integer","description":"ID"},"description":{"type":"string","description":"Description"},"number":{"type":"string","description":"Number"},"latest_revision_url":{"type":"string","description":"Url to PDF view"}}},"trade":{"type":"object","properties":{"id":{"type":"integer","description":"Trade ID"},"name":{"type":"string","description":"Trade name"},"active":{"type":"boolean","description":"Trade availability"},"updated_at":{"type":"string","description":"Timestamp of last update to Trade","format":"date-time"}}},"type":{"type":"object","required":["id","category","category_id","name"],"properties":{"id":{"type":"integer","description":"Observation Type ID"},"category":{"type":"string","description":"Observation Type category","enum":["Quality","Safety","Commissioning","Warranty","Work to Complete"]},"category_key":{"type":"string","description":"Observation Type category (snake_case)"},"category_id":{"type":"integer","description":"Observation Category ID"},"name":{"type":"string","description":"Type name"},"active":{"type":"boolean","description":"Flag denoting if the Observation Type is available for use"},"company_active":{"type":"boolean","description":"Flag denoting if the Company is available for use"},"parent_inactive":{"type":"boolean","description":"Flag denoting if the Parent is available for use"},"in_use":{"type":"boolean","description":"Flag denoting if the in use is available for use"},"kind":{"type":"string","description":"kind"},"name_translations":{"type":"object","description":"Company's custom translations for observation type","properties":{"en":{"type":"object","description":"(nested object)"},"es":{"type":"object","description":"(nested object)"},"fr-CA":{"type":"object","description":"(nested object)"},"en-AU":{"type":"object","description":"(nested object)"}}},"localized_name":{"type":"string","description":"returns the localized observation_type name. It'll return custom traslations depending on the param sent in."}}},"custom_fields":{"type":"object","properties":{"custom_field_%{custom_field_string_definition_id}":{"type":"object","properties":{"data_type":{"type":"object","description":"(nested object)"},"value":{"type":"object","description":"(nested object)"}}},"custom_field_%{custom_field_decimal_definition_id}":{"type":"object","properties":{"data_type":{"type":"object","description":"(nested object)"},"value":{"type":"object","description":"(nested object)"}}},"custom_field_%{custom_field_boolean_definition_id}":{"type":"object","properties":{"data_type":{"type":"object","description":"(nested object)"},"value":{"type":"object","description":"(nested object)"}}},"custom_field_%{custom_field_lov_entry_definition_id}":{"type":"object","properties":{"data_type":{"type":"object","description":"(nested object)"},"value":{"type":"object","description":"(nested object)"}}},"custom_field_%{custom_field_lov_entries_definition_id}":{"type":"object","properties":{"data_type":{"type":"object","description":"(nested object)"},"value":{"type":"object","description":"(nested object)"}}}}},"permissions":{"type":"object","description":"User permissions for this observation item","properties":{"can_edit":{"type":"boolean","description":"Whether the user can edit this observation item"}}}}}}},"400":{"description":"Bad Request"},"401":{"description":"Unauthorized"},"403":{"description":"Forbidden"}},"requestBody":{"contentType":"application/json","required":true,"schema":{"type":"object","required":["project_id"],"properties":{"project_id":{"type":"integer","description":"ID of the Project"}}}}}